bravado_types/__init__.py
bravado_types/__main__.py
bravado_types/config.py
bravado_types/data_model.py
bravado_types/extract.py
bravado_types/metadata.py
bravado_types/py.typed
bravado_types/render.py
bravado_types/types.py
bravado_types/templates/header.mako
bravado_types/templates/module.py.mako
bravado_types/templates/module.pyi.mako
bravado_types-1.0.1.dist-info/LICENSE
bravado_types-1.0.1.dist-info/METADATA
bravado_types-1.0.1.dist-info/WHEEL
bravado_types-1.0.1.dist-info/entry_points.txt
bravado_types-1.0.1.dist-info/top_level.txt
bravado_types-1.0.1.dist-info/RECORD
