Metadata-Version: 2.1
Name: bravado-types
Version: 1.0.1
Summary: Tool to generate MyPy type stubs for Bravado-generated classes to support static type checking.
Home-page: https://github.com/nickgaya/bravado-types
Author: Nicholas Gaya
Author-email: nickgaya@users.noreply.github.com
License: MIT License
Platform: UNKNOWN
Classifier: Topic :: Software Development :: Code Generators
Classifier: Development Status :: 5 - Production/Stable
Classifier: License :: OSI Approved :: MIT License
Classifier: Programming Language :: Python :: 3 :: Only
Classifier: Programming Language :: Python :: 3.6
Classifier: Programming Language :: Python :: 3.7
Classifier: Operating System :: OS Independent
Classifier: Intended Audience :: Developers
Classifier: Typing :: Typed
Requires-Dist: bravado (>=10.3.0)
Requires-Dist: bravado-core (>=5.14.0)
Requires-Dist: mako
Requires-Dist: setuptools
